odoo/addons/api_common_base/CHANGELOG.md
odoo/addons/api_common_base/README.rst
odoo/addons/api_common_base/__init__.py
odoo/addons/api_common_base/__manifest__.py
odoo/addons/api_common_base/controllers/__init__.py
odoo/addons/api_common_base/controllers/main.py
odoo/addons/api_common_base/demo/api_key.xml
odoo/addons/api_common_base/static/description/icon.png
odoo/addons/api_common_base/tests/__init__.py
odoo/addons/api_common_base/tests/common_service.py
odoo12_addon_api_common_base-12.0.0.1.2.dist-info/METADATA
odoo12_addon_api_common_base-12.0.0.1.2.dist-info/WHEEL
odoo12_addon_api_common_base-12.0.0.1.2.dist-info/top_level.txt
odoo12_addon_api_common_base-12.0.0.1.2.dist-info/RECORD
