Metadata-Version: 2.1
Name: odoo12-addon-api-common-base
Version: 12.0.0.1.2
Summary: REST API Common Controller
Home-page: https://gitlab.com/somitcoop/erp-research/odoo-helpdesk
Author: Som It Cooperatiu SCCL, Som Connexió SCCL, Odoo Community Association (OCA)
Author-email: support@odoo-community.org
License: AGPL-3
Platform: UNKNOWN
Classifier: Programming Language :: Python
Classifier: Framework :: Odoo
Classifier: Framework :: Odoo :: 12.0
Classifier: License :: OSI Approved :: GNU Affero General Public License v3
Requires-Python: >=3.5
Requires-Dist: odoo12-addon-auth-api-key
Requires-Dist: odoo12-addon-base-rest
Requires-Dist: odoo (<12.1dev,>=12.0a)
